capella_reader/__init__.py
capella_reader/_time.py
capella_reader/_types.py
capella_reader/_version.py
capella_reader/cli.py
capella_reader/collect.py
capella_reader/enums.py
capella_reader/geometry.py
capella_reader/image.py
capella_reader/metadata.py
capella_reader/orbit.py
capella_reader/polynomials.py
capella_reader/py.typed
capella_reader/radar.py
capella_reader/slc.py
capella_reader/adapters/__init__.py
capella_reader/adapters/isce3.py
capella_reader-0.2.0.dist-info/licenses/LICENSE.txt
capella_reader-0.2.0.dist-info/METADATA
capella_reader-0.2.0.dist-info/WHEEL
capella_reader-0.2.0.dist-info/entry_points.txt
capella_reader-0.2.0.dist-info/top_level.txt
capella_reader-0.2.0.dist-info/RECORD
