Metadata-Version: 2.4
Name: capella-reader
Version: 0.2.0
Summary: Basic models and reader for Capella SLCs
Author-email: Scott Staniewicz <scott.stanie@gmail.com>
License: MIT License
Project-URL: Homepage, https://github.com/scottstanie/capella-reader
Project-URL: Bug Tracker, https://github.com/scottstanie/capella-reader/issues
Project-URL: Discussions, https://github.com/scottstanie/capella-reader/discussions
Project-URL: Changelog, https://github.com/scottstanie/capella-reader/releases
Classifier: Intended Audience :: Developers
Classifier: Intended Audience :: Science/Research
Classifier: Programming Language :: Python :: 3
Classifier: Programming Language :: Python :: 3.11
Classifier: Programming Language :: Python :: 3.12
Classifier: Programming Language :: Python :: 3.13
Classifier: Programming Language :: Python :: 3.14
Classifier: Programming Language :: Python
Classifier: Topic :: Scientific/Engineering
Classifier: Typing :: Typed
Requires-Python: >=3.10
License-File: LICENSE.txt
Requires-Dist: numpy
Requires-Dist: pydantic>=2
Requires-Dist: tifffile
Requires-Dist: typing_extensions
Provides-Extra: fsspec
Requires-Dist: fsspec[http]; extra == "fsspec"
Provides-Extra: test
Requires-Dist: fsspec[http]; extra == "test"
Requires-Dist: pre-commit; extra == "test"
Requires-Dist: pytest; extra == "test"
Requires-Dist: pytest-cov; extra == "test"
Requires-Dist: pytest-randomly; extra == "test"
Requires-Dist: ruff; extra == "test"
Requires-Dist: ipython; extra == "test"
Provides-Extra: docs
Requires-Dist: mkdocs; extra == "docs"
Requires-Dist: mkdocs-gen-files; extra == "docs"
Requires-Dist: mkdocs-jupyter; extra == "docs"
Requires-Dist: mkdocs-literate-nav; extra == "docs"
Requires-Dist: mkdocs-material; extra == "docs"
Requires-Dist: pymdown-extensions; extra == "docs"
Requires-Dist: matplotlib; extra == "docs"
Requires-Dist: mkdocstrings[python]; extra == "docs"
Requires-Dist: mkdocs-section-index; extra == "docs"
Dynamic: license-file
